wierdpkg/__init__.py
wierdpkg/example.py
wierdpkg-0.0.1.dist-info/LICENSE
wierdpkg-0.0.1.dist-info/METADATA
wierdpkg-0.0.1.dist-info/WHEEL
wierdpkg-0.0.1.dist-info/top_level.txt
wierdpkg-0.0.1.dist-info/RECORD
