Metadata-Version: 2.1
Name: wierdpkg
Version: 0.0.1
Summary: An arch reactor package
Author-email: A React <areact@gmail.com>
Classifier: Programming Language :: Python :: 3
Classifier: License :: OSI Approved :: MIT License
Classifier: Operating System :: OS Independent
Requires-Python: >=3.7
License-File: LICENSE
